atom/__init__.py
atom/cli.py
atom/environment.py
atom/settings.py
atom/commons/__init__.py
atom/commons/exception.py
atom/commons/regex.py
atom/commons/shell.py
atom/core/AppSource.py
atom/core/Request.py
atom/core/Response.py
atom/core/URLController.py
atom/core/URLRoute.py
atom/core/__init__.py
atom_server-0.0.3.dist-info/LICENSE
atom_server-0.0.3.dist-info/METADATA
atom_server-0.0.3.dist-info/WHEEL
atom_server-0.0.3.dist-info/entry_points.txt
atom_server-0.0.3.dist-info/top_level.txt
atom_server-0.0.3.dist-info/RECORD
